{
  "users": [
    "Doug"
  ],
  "entries": [
    {
      "date": "2025-06-03",
      "user": "Doug",
      "calls": 3,
      "connections": 1,
      "email": 3,
      "sms": 2,
      "cma": 0,
      "form6 sent": 0,
      "form6 received": 0,
      "leads": 0,
      "appointments": 0,
      "appraisals": 0,
      "tasks": 0,
      "comments": "75/"
    },
    {
      "date": "2025-05-30",
      "user": "Doug",
      "calls": 12,
      "connections": 6,
      "email": 10,
      "sms": 0,
      "cma": 0,
      "form6 sent": 0,
      "form6 received": 0,
      "leads": 0,
      "appointments": 0,
      "appraisals": 0,
      "tasks": 21,
      "comments": "45/24"
    },
    {
      "date": "2025-05-29",
      "user": "Doug",
      "calls": 8,
      "connections": 4,
      "email": 8,
      "sms": 3,
      "cma": 0,
      "form6 sent": 0,
      "form6 received": 0,
      "leads": 0,
      "appointments": 0,
      "appraisals": 0,
      "tasks": 43,
      "comments": "66/23"
    },
    {
      "date": "2025-05-28",
      "user": "Doug",
      "calls": 10,
      "connections": 4,
      "email": 14,
      "sms": 0,
      "cma": 0,
      "form6 sent": 0,
      "form6 received": 0,
      "leads": 0,
      "appointments": 0,
      "appraisals": 0,
      "tasks": 0,
      "comments": "84/37"
    },
    {
      "date": "2025-05-27",
      "user": "Doug",
      "calls": 18,
      "connections": 14,
      "email": 6,
      "sms": 5,
      "cma": 0,
      "form6 sent": 0,
      "form6 received": 0,
      "leads": 0,
      "appointments": 0,
      "appraisals": 0,
      "tasks": 0,
      "comments": "77/60"
    },
    {
      "date": "2025-05-23",
      "user": "Doug",
      "calls": 1,
      "connections": 0,
      "email": 1,
      "sms": 1,
      "cma": 0,
      "form6 sent": 0,
      "form6 received": 0,
      "leads": 0,
      "appointments": 0,
      "appraisals": 0,
      "tasks": 12,
      "comments": "66/54"
    },
    {
      "date": "2025-05-22",
      "user": "Doug",
      "calls": 3,
      "connections": 2,
      "email": 6,
      "sms": 1,
      "cma": 0,
      "form6 sent": 0,
      "form6 received": 0,
      "leads": 0,
      "appointments": 0,
      "appraisals": 0,
      "tasks": 32,
      "comments": "84/52"
    },
    {
      "date": "2025-05-21",
      "user": "Doug",
      "calls": 10,
      "connections": 7,
      "email": 6,
      "sms": 0,
      "cma": 1,
      "form6 sent": 0,
      "form6 received": 0,
      "leads": 1,
      "appointments": 1,
      "appraisals": 0,
      "tasks": 22,
      "comments": "82/60"
    },
    {
      "date": "2025-05-20",
      "user": "Doug",
      "calls": 10,
      "connections": 6,
      "email": 8,
      "sms": 0,
      "cma": 0,
      "form6 sent": 0,
      "form6 received": 0,
      "leads": 0,
      "appointments": 0,
      "appraisals": 1,
      "tasks": 19,
      "comments": "81/62"
    },
    {
      "date": "2025-05-16",
      "user": "Doug",
      "calls": 3,
      "connections": 2,
      "email": 2,
      "sms": 0,
      "cma": 0,
      "form6 sent": 0,
      "form6 received": 0,
      "leads": 0,
      "appointments": 0,
      "appraisals": 0,
      "tasks": 0,
      "comments": "59/52"
    },
    {
      "date": "2025-05-15",
      "user": "Doug",
      "calls": 22,
      "connections": 16,
      "email": 24,
      "sms": 1,
      "cma": 0,
      "form6 sent": 0,
      "form6 received": 0,
      "leads": 0,
      "appointments": 0,
      "appraisals": 0,
      "tasks": 0,
      "comments": "84/47"
    },
    {
      "date": "2025-05-14",
      "user": "Doug",
      "calls": 20,
      "connections": 11,
      "email": 19,
      "sms": 0,
      "cma": 0,
      "form6 sent": 0,
      "form6 received": 0,
      "leads": 0,
      "appointments": 0,
      "appraisals": 0,
      "tasks": 39,
      "comments": "105/66"
    },
    {
      "date": "2025-05-13",
      "user": "Doug",
      "calls": 13,
      "connections": 8,
      "email": 5,
      "sms": 3,
      "cma": 0,
      "form6 sent": 0,
      "form6 received": 0,
      "leads": 0,
      "appointments": 0,
      "appraisals": 1,
      "tasks": 0,
      "comments": "96/85"
    },
    {
      "date": "2025-05-09",
      "user": "Doug",
      "calls": 8,
      "connections": 4,
      "email": 3,
      "sms": 1,
      "cma": 0,
      "form6 sent": 0,
      "form6 received": 0,
      "leads": 0,
      "appointments": 0,
      "appraisals": 0,
      "tasks": 19,
      "comments": "81/62"
    },
    {
      "date": "2025-05-08",
      "user": "Doug",
      "calls": 7,
      "connections": 4,
      "email": 49,
      "sms": 0,
      "cma": 2,
      "form6 sent": 0,
      "form6 received": 0,
      "leads": 0,
      "appointments": 0,
      "appraisals": 2,
      "tasks": 0,
      "comments": "84/75"
    },
    {
      "date": "2025-05-07",
      "user": "Doug",
      "calls": 0,
      "connections": 0,
      "email": 2,
      "sms": 0,
      "cma": 0,
      "form6 sent": 0,
      "form6 received": 0,
      "leads": 0,
      "appointments": 0,
      "appraisals": 0,
      "tasks": 0,
      "comments": null
    },
    {
      "date": "2025-04-30",
      "user": "Doug",
      "calls": 0,
      "connections": 0,
      "email": 51,
      "sms": 0,
      "cma": 0,
      "form6 sent": 0,
      "form6 received": 0,
      "leads": 0,
      "appointments": 0,
      "appraisals": 0,
      "tasks": 0,
      "comments": "94/42"
    },
    {
      "date": "2025-04-29",
      "user": "Doug",
      "calls": 4,
      "connections": 4,
      "email": 48,
      "sms": 35,
      "cma": 0,
      "form6 sent": 0,
      "form6 received": 0,
      "leads": 0,
      "appointments": 0,
      "appraisals": 0,
      "tasks": 0,
      "comments": "145/77"
    },
    {
      "date": "2025-04-24",
      "user": "Doug",
      "calls": 8,
      "connections": 6,
      "email": 3,
      "sms": 1,
      "cma": 0,
      "form6 sent": 0,
      "form6 received": 0,
      "leads": 0,
      "appointments": 0,
      "appraisals": 0,
      "tasks": 26,
      "comments": "141/115"
    },
    {
      "date": "2025-04-23",
      "user": "Doug",
      "calls": 2,
      "connections": 2,
      "email": 2,
      "sms": 0,
      "cma": 0,
      "form6 sent": 0,
      "form6 received": 0,
      "leads": 0,
      "appointments": 0,
      "appraisals": 0,
      "tasks": 26,
      "comments": "158/132"
    },
    {
      "date": "2025-04-22",
      "user": "Doug",
      "calls": 5,
      "connections": 3,
      "email": 18,
      "sms": 1,
      "cma": 0,
      "form6 sent": 0,
      "form6 received": 0,
      "leads": 0,
      "appointments": 0,
      "appraisals": 0,
      "tasks": 92,
      "comments": "234/142"
    },
    {
      "date": "2025-04-17",
      "user": "Doug",
      "calls": 3,
      "connections": 2,
      "email": 19,
      "sms": 1,
      "cma": 0,
      "form6 sent": 0,
      "form6 received": 0,
      "leads": 0,
      "appointments": 0,
      "appraisals": 0,
      "tasks": 66,
      "comments": "261/194"
    },
    {
      "date": "2025-04-16",
      "user": "Doug",
      "calls": 4,
      "connections": 4,
      "email": 0,
      "sms": 0,
      "cma": 0,
      "form6 sent": 0,
      "form6 received": 0,
      "leads": 0,
      "appointments": 0,
      "appraisals": 0,
      "tasks": 19,
      "comments": "277/258"
    },
    {
      "date": "2025-04-15",
      "user": "Doug",
      "calls": 13,
      "connections": 2,
      "email": 8,
      "sms": 5,
      "cma": 0,
      "form6 sent": 0,
      "form6 received": 0,
      "leads": 0,
      "appointments": 0,
      "appraisals": 0,
      "tasks": 34,
      "comments": "292/258"
    },
    {
      "date": "2025-04-14",
      "user": "Doug",
      "calls": 3,
      "connections": 1,
      "email": 8,
      "sms": 0,
      "cma": 0,
      "form6 sent": 0,
      "form6 received": 0,
      "leads": 0,
      "appointments": 0,
      "appraisals": 0,
      "tasks": 9,
      "comments": "301/282"
    },
    {
      "date": "2025-04-11",
      "user": "Doug",
      "calls": 5,
      "connections": 2,
      "email": 2,
      "sms": 1,
      "cma": 0,
      "form6 sent": 0,
      "form6 received": 0,
      "leads": 0,
      "appointments": 0,
      "appraisals": 0,
      "tasks": 0,
      "comments": "292/287"
    },
    {
      "date": "2025-04-10",
      "user": "Doug",
      "calls": 11,
      "connections": 7,
      "email": 12,
      "sms": 2,
      "cma": 0,
      "form6 sent": 0,
      "form6 received": 0,
      "leads": 0,
      "appointments": 0,
      "appraisals": 0,
      "tasks": 0,
      "comments": "314/"
    },
    {
      "date": "2025-04-09",
      "user": "Doug",
      "calls": 10,
      "connections": 4,
      "email": 17,
      "sms": 8,
      "cma": 0,
      "form6 sent": 0,
      "form6 received": 0,
      "leads": 0,
      "appointments": 0,
      "appraisals": 0,
      "tasks": 29,
      "comments": "351/322"
    },
    {
      "date": "2025-04-03",
      "user": "Doug",
      "calls": 11,
      "connections": 5,
      "email": 13,
      "sms": 2,
      "cma": 0,
      "form6 sent": 1,
      "form6 received": 0,
      "leads": 0,
      "appointments": 2,
      "appraisals": 0,
      "tasks": 27,
      "comments": "255/228"
    },
    {
      "date": "2025-04-02",
      "user": "Doug",
      "calls": 15,
      "connections": 8,
      "email": 12,
      "sms": 3,
      "cma": 0,
      "form6 sent": 0,
      "form6 received": 0,
      "leads": 0,
      "appointments": 1,
      "appraisals": 0,
      "tasks": 34,
      "comments": "283/249"
    },
    {
      "date": "2025-04-01",
      "user": "Doug",
      "calls": 2,
      "connections": 1,
      "email": 3,
      "sms": 1,
      "cma": 0,
      "form6 sent": 0,
      "form6 received": 0,
      "leads": 0,
      "appointments": 0,
      "appraisals": 0,
      "tasks": 0,
      "comments": "303/"
    },
    {
      "date": "2025-03-31",
      "user": "Doug",
      "calls": 22,
      "connections": 12,
      "email": 9,
      "sms": 6,
      "cma": 0,
      "form6 sent": 0,
      "form6 received": 0,
      "leads": 0,
      "appointments": 0,
      "appraisals": 0,
      "tasks": 41,
      "comments": "320/279"
    },
    {
      "date": "2025-03-28",
      "user": "Doug",
      "calls": 4,
      "connections": 3,
      "email": 2400,
      "sms": 1,
      "cma": 0,
      "form6 sent": 0,
      "form6 received": 0,
      "leads": 0,
      "appointments": 1,
      "appraisals": 1,
      "tasks": 0,
      "comments": null
    },
    {
      "date": "2025-03-26",
      "user": "Doug",
      "calls": 8,
      "connections": 4,
      "email": 2,
      "sms": 5,
      "cma": 0,
      "form6 sent": 0,
      "form6 received": 0,
      "leads": 0,
      "appointments": 1,
      "appraisals": 0,
      "tasks": 15,
      "comments": "379/364"
    },
    {
      "date": "2025-03-25",
      "user": "Doug",
      "calls": 37,
      "connections": 14,
      "email": 3,
      "sms": 14,
      "cma": 0,
      "form6 sent": 0,
      "form6 received": 0,
      "leads": 0,
      "appointments": 2,
      "appraisals": 1,
      "tasks": 18,
      "comments": "410/392"
    },
    {
      "date": "2025-03-24",
      "user": "Doug",
      "calls": 25,
      "connections": 10,
      "email": 6,
      "sms": 11,
      "cma": 0,
      "form6 sent": 0,
      "form6 received": 0,
      "leads": 0,
      "appointments": 0,
      "appraisals": 1,
      "tasks": 0,
      "comments": "437/"
    },
    {
      "date": "2025-03-21",
      "user": "Doug",
      "calls": 5,
      "connections": 3,
      "email": 1,
      "sms": 0,
      "cma": 0,
      "form6 sent": 0,
      "form6 received": 0,
      "leads": 0,
      "appointments": 0,
      "appraisals": 0,
      "tasks": 0,
      "comments": "407/"
    },
    {
      "date": "2025-03-20",
      "user": "Doug",
      "calls": 7,
      "connections": 4,
      "email": 64,
      "sms": 0,
      "cma": 0,
      "form6 sent": 0,
      "form6 received": 0,
      "leads": 0,
      "appointments": 0,
      "appraisals": 0,
      "tasks": 0,
      "comments": "422"
    },
    {
      "date": "2025-03-19",
      "user": "Doug",
      "calls": 0,
      "connections": 0,
      "email": 0,
      "sms": 0,
      "cma": 0,
      "form6 sent": 0,
      "form6 received": 0,
      "leads": 0,
      "appointments": 0,
      "appraisals": 0,
      "tasks": 0,
      "comments": null
    },
    {
      "date": "2025-03-18",
      "user": "Doug",
      "calls": 4,
      "connections": 4,
      "email": 5,
      "sms": 3,
      "cma": 0,
      "form6 sent": 0,
      "form6 received": 0,
      "leads": 0,
      "appointments": 0,
      "appraisals": 0,
      "tasks": 0,
      "comments": "350"
    },
    {
      "date": "2025-03-17",
      "user": "Doug",
      "calls": 24,
      "connections": 13,
      "email": 5,
      "sms": 12,
      "cma": 0,
      "form6 sent": 0,
      "form6 received": 0,
      "leads": 0,
      "appointments": 3,
      "appraisals": 2,
      "tasks": 5,
      "comments": null
    },
    {
      "date": "2025-03-13",
      "user": "Doug",
      "calls": 0,
      "connections": 0,
      "email": 0,
      "sms": 0,
      "cma": 0,
      "form6 sent": 0,
      "form6 received": 0,
      "leads": 0,
      "appointments": 0,
      "appraisals": 0,
      "tasks": 0,
      "comments": null
    },
    {
      "date": "2025-03-12",
      "user": "Doug",
      "calls": 5,
      "connections": 0,
      "email": 1,
      "sms": 2,
      "cma": 0,
      "form6 sent": 0,
      "form6 received": 0,
      "leads": 0,
      "appointments": 0,
      "appraisals": 0,
      "tasks": 1317,
      "comments": "1319"
    },
    {
      "date": "2025-03-10",
      "user": "Doug",
      "calls": 1,
      "connections": 1,
      "email": 0,
      "sms": 0,
      "cma": 0,
      "form6 sent": 0,
      "form6 received": 0,
      "leads": 0,
      "appointments": 0,
      "appraisals": 1,
      "tasks": 0,
      "comments": null
    },
    {
      "date": "2025-03-05",
      "user": "Doug",
      "calls": 0,
      "connections": 0,
      "email": 0,
      "sms": 0,
      "cma": 0,
      "form6 sent": 0,
      "form6 received": 0,
      "leads": 0,
      "appointments": 0,
      "appraisals": 0,
      "tasks": 0,
      "comments": null
    },
    {
      "date": "2025-03-04",
      "user": "Doug",
      "calls": 22,
      "connections": 7,
      "email": 2,
      "sms": 15,
      "cma": 0,
      "form6 sent": 0,
      "form6 received": 0,
      "leads": 0,
      "appointments": 0,
      "appraisals": 0,
      "tasks": 0,
      "comments": null
    },
    {
      "date": "2025-02-27",
      "user": "Doug",
      "calls": 8,
      "connections": 6,
      "email": 3,
      "sms": 4,
      "cma": 0,
      "form6 sent": 0,
      "form6 received": 0,
      "leads": 0,
      "appointments": 0,
      "appraisals": 0,
      "tasks": 0,
      "comments": null
    },
    {
      "date": "2025-02-25",
      "user": "Doug",
      "calls": 21,
      "connections": 6,
      "email": 0,
      "sms": 12,
      "cma": 0,
      "form6 sent": 0,
      "form6 received": 0,
      "leads": 0,
      "appointments": 0,
      "appraisals": 0,
      "tasks": 0,
      "comments": null
    },
    {
      "date": "2025-02-20",
      "user": "Doug",
      "calls": 11,
      "connections": 10,
      "email": 3001,
      "sms": 3,
      "cma": 0,
      "form6 sent": 0,
      "form6 received": 0,
      "leads": 0,
      "appointments": 2,
      "appraisals": 0,
      "tasks": 0,
      "comments": null
    },
    {
      "date": "2025-02-19",
      "user": "Doug",
      "calls": 6,
      "connections": 5,
      "email": 0,
      "sms": 0,
      "cma": 0,
      "form6 sent": 0,
      "form6 received": 0,
      "leads": 0,
      "appointments": 0,
      "appraisals": 0,
      "tasks": 0,
      "comments": "1018/1015"
    },
    {
      "date": "2025-02-18",
      "user": "Doug",
      "calls": 3,
      "connections": 1,
      "email": 5,
      "sms": 0,
      "cma": 0,
      "form6 sent": 0,
      "form6 received": 0,
      "leads": 0,
      "appointments": 0,
      "appraisals": 0,
      "tasks": 15,
      "comments": "990/975"
    },
    {
      "date": "2025-02-14",
      "user": "Doug",
      "calls": 3,
      "connections": 3,
      "email": 2,
      "sms": 1,
      "cma": 0,
      "form6 sent": 0,
      "form6 received": 0,
      "leads": 0,
      "appointments": 0,
      "appraisals": 0,
      "tasks": 0,
      "comments": "340/"
    },
    {
      "date": "2025-02-13",
      "user": "Doug",
      "calls": 3,
      "connections": 0,
      "email": 19,
      "sms": 1,
      "cma": 0,
      "form6 sent": 0,
      "form6 received": 0,
      "leads": 0,
      "appointments": 1,
      "appraisals": 1,
      "tasks": 3,
      "comments": "333/330"
    },
    {
      "date": "2025-02-12",
      "user": "Doug",
      "calls": 9,
      "connections": 3,
      "email": 3,
      "sms": 1,
      "cma": 0,
      "form6 sent": 0,
      "form6 received": 0,
      "leads": 0,
      "appointments": 0,
      "appraisals": 0,
      "tasks": 18,
      "comments": "344/326"
    },
    {
      "date": "2025-02-11",
      "user": "Doug",
      "calls": 6,
      "connections": 3,
      "email": 2,
      "sms": 0,
      "cma": 0,
      "form6 sent": 0,
      "form6 received": 0,
      "leads": 0,
      "appointments": 0,
      "appraisals": 0,
      "tasks": 36,
      "comments": "366/330"
    },
    {
      "date": "2025-02-10",
      "user": "Doug",
      "calls": 9,
      "connections": 3,
      "email": 6,
      "sms": 2,
      "cma": 0,
      "form6 sent": 0,
      "form6 received": 0,
      "leads": 0,
      "appointments": 0,
      "appraisals": 0,
      "tasks": 47,
      "comments": "410/363"
    },
    {
      "date": "2025-01-16",
      "user": "Doug",
      "calls": 6,
      "connections": 3,
      "email": 8,
      "sms": 1,
      "cma": 0,
      "form6 sent": 0,
      "form6 received": 0,
      "leads": 0,
      "appointments": 0,
      "appraisals": 0,
      "tasks": 0,
      "comments": "234/212"
    },
    {
      "date": "2025-01-14",
      "user": "Doug",
      "calls": 8,
      "connections": 4,
      "email": 11,
      "sms": 3,
      "cma": 0,
      "form6 sent": 1,
      "form6 received": 0,
      "leads": 0,
      "appointments": 1,
      "appraisals": 0,
      "tasks": 48,
      "comments": "258/210"
    },
    {
      "date": "2025-01-13",
      "user": "Doug",
      "calls": 4,
      "connections": 3,
      "email": 3,
      "sms": 0,
      "cma": 0,
      "form6 sent": 0,
      "form6 received": 0,
      "leads": 0,
      "appointments": 0,
      "appraisals": 0,
      "tasks": 5,
      "comments": "254/249"
    },
    {
      "date": "2025-01-10",
      "user": "Doug",
      "calls": 5,
      "connections": 2,
      "email": 10,
      "sms": 3,
      "cma": 0,
      "form6 sent": 0,
      "form6 received": 0,
      "leads": 0,
      "appointments": 0,
      "appraisals": 0,
      "tasks": 33,
      "comments": "267/234"
    },
    {
      "date": "2025-01-09",
      "user": "Doug",
      "calls": 14,
      "connections": 5,
      "email": 15,
      "sms": 5,
      "cma": 0,
      "form6 sent": 0,
      "form6 received": 0,
      "leads": 0,
      "appointments": 0,
      "appraisals": 0,
      "tasks": 50,
      "comments": "304//254"
    },
    {
      "date": "2025-01-08",
      "user": "Doug",
      "calls": 14,
      "connections": 10,
      "email": 4,
      "sms": 5,
      "cma": 0,
      "form6 sent": 0,
      "form6 received": 0,
      "leads": 0,
      "appointments": 0,
      "appraisals": 0,
      "tasks": 27,
      "comments": "298-271"
    },
    {
      "date": "2025-01-07",
      "user": "Doug",
      "calls": 9,
      "connections": 4,
      "email": 3,
      "sms": 0,
      "cma": 0,
      "form6 sent": 0,
      "form6 received": 0,
      "leads": 0,
      "appointments": 0,
      "appraisals": 0,
      "tasks": 10,
      "comments": "61/51"
    },
    {
      "date": "2025-01-03",
      "user": "Doug",
      "calls": 0,
      "connections": 0,
      "email": 0,
      "sms": 0,
      "cma": 0,
      "form6 sent": 0,
      "form6 received": 0,
      "leads": 0,
      "appointments": 0,
      "appraisals": 0,
      "tasks": 0,
      "comments": null
    },
    {
      "date": "2025-01-02",
      "user": "Doug",
      "calls": 2,
      "connections": 2,
      "email": 0,
      "sms": 0,
      "cma": 0,
      "form6 sent": 0,
      "form6 received": 0,
      "leads": 0,
      "appointments": 0,
      "appraisals": 0,
      "tasks": 16,
      "comments": "47/31"
    },
    {
      "date": "2024-12-24",
      "user": "Doug",
      "calls": 6,
      "connections": 4,
      "email": 4,
      "sms": 3,
      "cma": 0,
      "form6 sent": 0,
      "form6 received": 0,
      "leads": 0,
      "appointments": 0,
      "appraisals": 0,
      "tasks": 40,
      "comments": "60/20"
    },
    {
      "date": "2024-12-20",
      "user": "Doug",
      "calls": 1,
      "connections": 0,
      "email": 1,
      "sms": 1,
      "cma": 0,
      "form6 sent": 0,
      "form6 received": 0,
      "leads": 0,
      "appointments": 0,
      "appraisals": 0,
      "tasks": 7,
      "comments": "7-0"
    },
    {
      "date": "2024-12-19",
      "user": "Doug",
      "calls": 6,
      "connections": 4,
      "email": 3,
      "sms": 3,
      "cma": 0,
      "form6 sent": 0,
      "form6 received": 0,
      "leads": 0,
      "appointments": 0,
      "appraisals": 0,
      "tasks": 10,
      "comments": "10-0"
    },
    {
      "date": "2024-12-18",
      "user": "Doug",
      "calls": 10,
      "connections": 6,
      "email": 9,
      "sms": 2,
      "cma": 0,
      "form6 sent": 0,
      "form6 received": 0,
      "leads": 0,
      "appointments": 0,
      "appraisals": 0,
      "tasks": 18,
      "comments": "18-0"
    },
    {
      "date": "2024-12-17",
      "user": "Doug",
      "calls": 14,
      "connections": 6,
      "email": 6,
      "sms": 1,
      "cma": 0,
      "form6 sent": 0,
      "form6 received": 0,
      "leads": 0,
      "appointments": 1,
      "appraisals": 0,
      "tasks": 23,
      "comments": "23-0"
    },
    {
      "date": "2024-12-16",
      "user": "Doug",
      "calls": 8,
      "connections": 4,
      "email": 15,
      "sms": 2,
      "cma": 0,
      "form6 sent": 0,
      "form6 received": 0,
      "leads": 0,
      "appointments": 0,
      "appraisals": 0,
      "tasks": 56,
      "comments": "56 - 0"
    },
    {
      "date": "2024-12-14",
      "user": "Doug",
      "calls": 10,
      "connections": 5,
      "email": 8,
      "sms": 0,
      "cma": 0,
      "form6 sent": 0,
      "form6 received": 0,
      "leads": 0,
      "appointments": 0,
      "appraisals": 0,
      "tasks": 25,
      "comments": "(55)72-47"
    },
    {
      "date": "2024-12-13",
      "user": "Doug",
      "calls": 12,
      "connections": 7,
      "email": 8,
      "sms": 2,
      "cma": 0,
      "form6 sent": 0,
      "form6 received": 0,
      "leads": 0,
      "appointments": 0,
      "appraisals": 0,
      "tasks": 22,
      "comments": "83-61"
    },
    {
      "date": "2024-12-12",
      "user": "Doug",
      "calls": 15,
      "connections": 8,
      "email": 9,
      "sms": 1,
      "cma": 0,
      "form6 sent": 0,
      "form6 received": 0,
      "leads": 0,
      "appointments": 0,
      "appraisals": 0,
      "tasks": 31,
      "comments": "93-62"
    },
    {
      "date": "2024-12-11",
      "user": "Doug",
      "calls": 16,
      "connections": 10,
      "email": 7,
      "sms": 0,
      "cma": 0,
      "form6 sent": 0,
      "form6 received": 0,
      "leads": 0,
      "appointments": 0,
      "appraisals": 0,
      "tasks": 20,
      "comments": "107-87"
    },
    {
      "date": "2024-12-10",
      "user": "Doug",
      "calls": 15,
      "connections": 7,
      "email": 4,
      "sms": 3,
      "cma": 0,
      "form6 sent": 0,
      "form6 received": 0,
      "leads": 0,
      "appointments": 0,
      "appraisals": 1,
      "tasks": 34,
      "comments": "115-81"
    },
    {
      "date": "2024-12-06",
      "user": "Doug",
      "calls": 7,
      "connections": 4,
      "email": 6,
      "sms": 1,
      "cma": 0,
      "form6 sent": 0,
      "form6 received": 0,
      "leads": 0,
      "appointments": 0,
      "appraisals": 0,
      "tasks": 10,
      "comments": "96-86"
    },
    {
      "date": "2024-12-05",
      "user": "Doug",
      "calls": 33,
      "connections": 17,
      "email": 20,
      "sms": 3,
      "cma": 0,
      "form6 sent": 0,
      "form6 received": 0,
      "leads": 0,
      "appointments": 0,
      "appraisals": 0,
      "tasks": 43,
      "comments": "121 - 78"
    },
    {
      "date": "2024-12-04",
      "user": "Doug",
      "calls": 6,
      "connections": 4,
      "email": 2,
      "sms": 4,
      "cma": 0,
      "form6 sent": 0,
      "form6 received": 0,
      "leads": 0,
      "appointments": 0,
      "appraisals": 0,
      "tasks": 12,
      "comments": "122-110"
    },
    {
      "date": "2024-12-03",
      "user": "Doug",
      "calls": 11,
      "connections": 6,
      "email": 4,
      "sms": 0,
      "cma": 0,
      "form6 sent": 0,
      "form6 received": 0,
      "leads": 0,
      "appointments": 0,
      "appraisals": 0,
      "tasks": 10,
      "comments": "Start 105 - 95"
    },
    {
      "date": "2024-11-30",
      "user": "Doug",
      "calls": 1,
      "connections": 1,
      "email": 50,
      "sms": 0,
      "cma": 0,
      "form6 sent": 0,
      "form6 received": 0,
      "leads": 0,
      "appointments": 0,
      "appraisals": 0,
      "tasks": 3,
      "comments": "78"
    },
    {
      "date": "2024-11-29",
      "user": "Doug",
      "calls": 4,
      "connections": 1,
      "email": 4,
      "sms": 0,
      "cma": 0,
      "form6 sent": 0,
      "form6 received": 0,
      "leads": 0,
      "appointments": 0,
      "appraisals": 0,
      "tasks": 18,
      "comments": "Tasks start: 76 f 58"
    },
    {
      "date": "2024-11-28",
      "user": "Doug",
      "calls": 14,
      "connections": 11,
      "email": 6,
      "sms": 3,
      "cma": 0,
      "form6 sent": 0,
      "form6 received": 0,
      "leads": 0,
      "appointments": 0,
      "appraisals": 0,
      "tasks": 90,
      "comments": "Tasks 151 - end 61"
    },
    {
      "date": "2024-11-27",
      "user": "Doug",
      "calls": 9,
      "connections": 7,
      "email": 10,
      "sms": 4,
      "cma": 0,
      "form6 sent": 0,
      "form6 received": 0,
      "leads": 0,
      "appointments": 0,
      "appraisals": 0,
      "tasks": 19,
      "comments": "Task start 154 / 135"
    },
    {
      "date": "2024-11-26",
      "user": "Doug",
      "calls": 5,
      "connections": 4,
      "email": 2,
      "sms": 1,
      "cma": 0,
      "form6 sent": 0,
      "form6 received": 0,
      "leads": 0,
      "appointments": 0,
      "appraisals": 0,
      "tasks": 19,
      "comments": "Start 157 Tasks F 138"
    },
    {
      "date": "2024-11-22",
      "user": "Doug",
      "calls": 17,
      "connections": 10,
      "email": 19,
      "sms": 0,
      "cma": 0,
      "form6 sent": 0,
      "form6 received": 0,
      "leads": 0,
      "appointments": 0,
      "appraisals": 0,
      "tasks": 44,
      "comments": "Task start 183 Fin 139"
    },
    {
      "date": "2024-11-21",
      "user": "Doug",
      "calls": 15,
      "connections": 5,
      "email": 17,
      "sms": 4,
      "cma": 0,
      "form6 sent": 0,
      "form6 received": 0,
      "leads": 0,
      "appointments": 0,
      "appraisals": 0,
      "tasks": 41,
      "comments": "Start 219 tasks to 178"
    },
    {
      "date": "2024-11-20",
      "user": "Doug",
      "calls": 15,
      "connections": 9,
      "email": 14,
      "sms": 4,
      "cma": 0,
      "form6 sent": 0,
      "form6 received": 0,
      "leads": 0,
      "appointments": 0,
      "appraisals": 0,
      "tasks": 44,
      "comments": "Start 255 fin 211"
    },
    {
      "date": "2024-11-19",
      "user": "Doug",
      "calls": 6,
      "connections": 5,
      "email": 13,
      "sms": 2,
      "cma": 0,
      "form6 sent": 0,
      "form6 received": 0,
      "leads": 0,
      "appointments": 0,
      "appraisals": 0,
      "tasks": 0,
      "comments": "Tasks 295 at start 250 end of day"
    },
    {
      "date": "2024-11-15",
      "user": "Doug",
      "calls": 5,
      "connections": 3,
      "email": 3,
      "sms": 2,
      "cma": 0,
      "form6 sent": 0,
      "form6 received": 0,
      "leads": 0,
      "appointments": 0,
      "appraisals": 0,
      "tasks": 0,
      "comments": "Start 292 tasks end 281 tasks"
    },
    {
      "date": "2024-11-13",
      "user": "Doug",
      "calls": 18,
      "connections": 11,
      "email": 6,
      "sms": 4,
      "cma": 0,
      "form6 sent": 0,
      "form6 received": 0,
      "leads": 0,
      "appointments": 0,
      "appraisals": 0,
      "tasks": 0,
      "comments": "to do list 347 at end of day"
    },
    {
      "date": "2024-10-03",
      "user": "Doug",
      "calls": 16,
      "connections": 6,
      "email": 7,
      "sms": 5,
      "cma": 0,
      "form6 sent": 0,
      "form6 received": 0,
      "leads": 0,
      "appointments": 0,
      "appraisals": 0,
      "tasks": 0,
      "comments": null
    },
    {
      "date": "2024-09-30",
      "user": "Doug",
      "calls": 4,
      "connections": 3,
      "email": 4200,
      "sms": 3,
      "cma": 0,
      "form6 sent": 0,
      "form6 received": 0,
      "leads": 1,
      "appointments": 1,
      "appraisals": 0,
      "tasks": 0,
      "comments": null
    },
    {
      "date": "2024-09-26",
      "user": "Doug",
      "calls": 0,
      "connections": 0,
      "email": 0,
      "sms": 0,
      "cma": 0,
      "form6 sent": 0,
      "form6 received": 0,
      "leads": 0,
      "appointments": 0,
      "appraisals": 0,
      "tasks": 0,
      "comments": null
    },
    {
      "date": "2024-09-25",
      "user": "Doug",
      "calls": 5,
      "connections": 4,
      "email": 6,
      "sms": 3,
      "cma": 1,
      "form6 sent": 1,
      "form6 received": 0,
      "leads": 1,
      "appointments": 2,
      "appraisals": 1,
      "tasks": 0,
      "comments": "129 Fernberg"
    },
    {
      "date": "2024-09-25",
      "user": "Doug",
      "calls": 5,
      "connections": 4,
      "email": 6,
      "sms": 3,
      "cma": 1,
      "form6 sent": 1,
      "form6 received": 0,
      "leads": 1,
      "appointments": 2,
      "appraisals": 1,
      "tasks": 0,
      "comments": "129 Fernberg"
    },
    {
      "date": "2024-09-24",
      "user": "Doug",
      "calls": 5,
      "connections": 3,
      "email": 4,
      "sms": 2,
      "cma": 0,
      "form6 sent": 0,
      "form6 received": 0,
      "leads": 1,
      "appointments": 1,
      "appraisals": 0,
      "tasks": 0,
      "comments": null
    },
    {
      "date": "2024-09-23",
      "user": "Doug",
      "calls": 5,
      "connections": 4,
      "email": 2,
      "sms": 1,
      "cma": 0,
      "form6 sent": 0,
      "form6 received": 0,
      "leads": 0,
      "appointments": 0,
      "appraisals": 0,
      "tasks": 0,
      "comments": null
    },
    {
      "date": "2024-09-19",
      "user": "Doug",
      "calls": 10,
      "connections": 4,
      "email": 2859,
      "sms": 6,
      "cma": 0,
      "form6 sent": 0,
      "form6 received": 0,
      "leads": 0,
      "appointments": 0,
      "appraisals": 0,
      "tasks": 0,
      "comments": null
    },
    {
      "date": "2024-09-17",
      "user": "Doug",
      "calls": 3,
      "connections": 0,
      "email": 159,
      "sms": 1,
      "cma": 0,
      "form6 sent": 0,
      "form6 received": 0,
      "leads": 0,
      "appointments": 0,
      "appraisals": 0,
      "tasks": 0,
      "comments": null
    },
    {
      "date": "2024-09-13",
      "user": "Doug",
      "calls": 7,
      "connections": 5,
      "email": 43,
      "sms": 0,
      "cma": 0,
      "form6 sent": 0,
      "form6 received": 0,
      "leads": 0,
      "appointments": 0,
      "appraisals": 0,
      "tasks": 0,
      "comments": null
    },
    {
      "date": "2024-09-12",
      "user": "Doug",
      "calls": 4,
      "connections": 4,
      "email": 12,
      "sms": 5,
      "cma": 0,
      "form6 sent": 0,
      "form6 received": 0,
      "leads": 0,
      "appointments": 0,
      "appraisals": 0,
      "tasks": 0,
      "comments": null
    },
    {
      "date": "2024-09-11",
      "user": "Doug",
      "calls": 16,
      "connections": 14,
      "email": 9,
      "sms": 5,
      "cma": 0,
      "form6 sent": 0,
      "form6 received": 0,
      "leads": 0,
      "appointments": 0,
      "appraisals": 0,
      "tasks": 0,
      "comments": null
    },
    {
      "date": "2024-09-09",
      "user": "Doug",
      "calls": 6,
      "connections": 4,
      "email": 2,
      "sms": 0,
      "cma": 0,
      "form6 sent": 0,
      "form6 received": 0,
      "leads": 0,
      "appointments": 0,
      "appraisals": 0,
      "tasks": 0,
      "comments": null
    },
    {
      "date": "2024-09-05",
      "user": "Doug",
      "calls": 4,
      "connections": 1,
      "email": 2156,
      "sms": 4,
      "cma": 0,
      "form6 sent": 0,
      "form6 received": 0,
      "leads": 1,
      "appointments": 0,
      "appraisals": 0,
      "tasks": 0,
      "comments": "new management lead for Jaclyn"
    },
    {
      "date": "2024-09-02",
      "user": "Doug",
      "calls": 6,
      "connections": 4,
      "email": 2,
      "sms": 1,
      "cma": 0,
      "form6 sent": 0,
      "form6 received": 0,
      "leads": 0,
      "appointments": 0,
      "appraisals": 0,
      "tasks": 0,
      "comments": null
    },
    {
      "date": "2024-08-29",
      "user": "Doug",
      "calls": 6,
      "connections": 4,
      "email": 3,
      "sms": 2,
      "cma": 0,
      "form6 sent": 0,
      "form6 received": 0,
      "leads": 1,
      "appointments": 0,
      "appraisals": 1,
      "tasks": 0,
      "comments": "The Witton: Jeremy Lloyd-Jones may be selling or renting."
    },
    {
      "date": "2024-08-28",
      "user": "Doug",
      "calls": 20,
      "connections": 13,
      "email": 4,
      "sms": 7,
      "cma": 0,
      "form6 sent": 0,
      "form6 received": 0,
      "leads": 0,
      "appointments": 1,
      "appraisals": 0,
      "tasks": 0,
      "comments": null
    },
    {
      "date": "2024-08-27",
      "user": "Doug",
      "calls": 14,
      "connections": 6,
      "email": 4,
      "sms": 9,
      "cma": 0,
      "form6 sent": 0,
      "form6 received": 0,
      "leads": 1,
      "appointments": 0,
      "appraisals": 0,
      "tasks": 0,
      "comments": "Reasonably good calls."
    },
    {
      "date": "2024-08-21",
      "user": "Doug",
      "calls": 8,
      "connections": 2,
      "email": 3,
      "sms": 6,
      "cma": 1,
      "form6 sent": 0,
      "form6 received": 0,
      "leads": 0,
      "appointments": 0,
      "appraisals": 0,
      "tasks": 0,
      "comments": "Morning Session"
    }
  ]
}